tilingsgui/__init__.py
tilingsgui/app.py
tilingsgui/events.py
tilingsgui/files.py
tilingsgui/geometry.py
tilingsgui/graphics.py
tilingsgui/main.py
tilingsgui/menu.py
tilingsgui/resources/img/png/add_custom.png
tilingsgui/resources/img/png/add_point.png
tilingsgui/resources/img/png/export.png
tilingsgui/resources/img/png/factor.png
tilingsgui/resources/img/png/factor_int.png
tilingsgui/resources/img/png/fusion_c.png
tilingsgui/resources/img/png/fusion_comp_c.png
tilingsgui/resources/img/png/fusion_comp_r.png
tilingsgui/resources/img/png/fusion_r.png
tilingsgui/resources/img/png/htc.png
tilingsgui/resources/img/png/move.png
tilingsgui/resources/img/png/obstr_trans.png
tilingsgui/resources/img/png/place_east.png
tilingsgui/resources/img/png/place_north.png
tilingsgui/resources/img/png/place_south.png
tilingsgui/resources/img/png/place_west.png
tilingsgui/resources/img/png/pplace_east.png
tilingsgui/resources/img/png/pplace_north.png
tilingsgui/resources/img/png/pplace_south.png
tilingsgui/resources/img/png/pplace_west.png
tilingsgui/resources/img/png/pretty.png
tilingsgui/resources/img/png/redo.png
tilingsgui/resources/img/png/rowcolsep.png
tilingsgui/resources/img/png/sequence.png
tilingsgui/resources/img/png/shading.png
tilingsgui/resources/img/png/show_cross.png
tilingsgui/resources/img/png/show_local.png
tilingsgui/resources/img/png/str.png
tilingsgui/resources/img/png/undo.png
tilingsgui/resources/img/png/verification.png
tilingsgui/resources/img/svg/add_custom.svg
tilingsgui/resources/img/svg/add_point.svg
tilingsgui/resources/img/svg/export.svg
tilingsgui/resources/img/svg/factor.svg
tilingsgui/resources/img/svg/factor_int.svg
tilingsgui/resources/img/svg/fusion_c.svg
tilingsgui/resources/img/svg/fusion_comp_c.svg
tilingsgui/resources/img/svg/fusion_comp_r.svg
tilingsgui/resources/img/svg/fusion_r.svg
tilingsgui/resources/img/svg/htc.svg
tilingsgui/resources/img/svg/move.svg
tilingsgui/resources/img/svg/obstr_trans.svg
tilingsgui-0.1.0.dist-info/entry_points.txt
tilingsgui-0.1.0.dist-info/LICENSE
tilingsgui-0.1.0.dist-info/WHEEL
tilingsgui-0.1.0.dist-info/METADATA
tilingsgui-0.1.0.dist-info/RECORD
